es_lmr_iwf_api_helper/__init__.py
es_lmr_iwf_api_helper/application.py
es_lmr_iwf_api_helper/config.py
es_lmr_iwf_api_helper/dao.py
es_lmr_iwf_api_helper/errors.py
es_lmr_iwf_api_helper/extensions.py
es_lmr_iwf_api_helper/flask_extensions.py
es_lmr_iwf_api_helper/logger.py
es_lmr_iwf_api_helper/monitoring.py
es_lmr_iwf_api_helper/routes.py
es_lmr_iwf_api_helper/static_config.py
es_lmr_iwf_api_helper-1.2.28.dist-info/METADATA
es_lmr_iwf_api_helper-1.2.28.dist-info/WHEEL
es_lmr_iwf_api_helper-1.2.28.dist-info/top_level.txt
es_lmr_iwf_api_helper-1.2.28.dist-info/RECORD
